pynps/__init__.py
pynps/cli/__init__.py
pynps/cli/cli.py
pynps/functions/__init__.py
pynps/functions/functions.py
pynps/variables/__init__.py
pynps/variables/variables.py
pynps-1.6.2.post2.dist-info/LICENSE
pynps-1.6.2.post2.dist-info/METADATA
pynps-1.6.2.post2.dist-info/WHEEL
pynps-1.6.2.post2.dist-info/entry_points.txt
pynps-1.6.2.post2.dist-info/top_level.txt
pynps-1.6.2.post2.dist-info/RECORD
