Metadata-Version: 2.1
Name: pynps
Version: 1.6.2.post2
Summary: PyNPS is a Nopaystation client writen in python.
Home-page: https://github.com/me/myproject
Author: evertonstz
Author-email: everton@protonmail.com
License: GPL3
Platform: UNKNOWN
Classifier: License :: OSI Approved :: GNU General Public License v3 (GPLv3)
Classifier: Operating System :: POSIX :: Linux
Classifier: Operating System :: Microsoft :: Windows
Classifier: Programming Language :: Python
Classifier: Programming Language :: Python :: 3
Classifier: Programming Language :: Python :: 3.8
Classifier: Programming Language :: Python :: Implementation :: CPython
Classifier: Programming Language :: Python :: Implementation :: PyPy
Requires-Python: >=3.7.0
Requires-Dist: prompt-toolkit
Requires-Dist: sqlitedict
